irmsd-0.1.1.dist-info/RECORD
irmsd-0.1.1.dist-info/WHEEL
irmsd-0.1.1.dist-info/entry_points.txt
irmsd-0.1.1.dist-info/METADATA
irmsd-0.1.1.dist-info/licenses/LICENSE
irmsd/_version.py
irmsd/__init__.py
irmsd/cli.py
irmsd/libirmsd_fortran.dylib
irmsd/_lib.py
irmsd/core/molecule.py
irmsd/core/__init__.py
irmsd/_fortran/CMakeLists.txt
irmsd/_fortran/.gitignore
irmsd/_fortran/fmods/utilities.f90
irmsd/_fortran/fmods/CMakeLists.txt
irmsd/_fortran/fmods/axis_exposed.f90
irmsd/_fortran/fmods/cn_exposed.f90
irmsd/_fortran/fmods/canonical_exposed.f90
irmsd/_fortran/fmods/sorter_exposed.f90
irmsd/_fortran/fmods/rotanisotrop.f90
irmsd/_fortran/fmods/term_ui.f90
irmsd/_fortran/fmods/irmsd_exposed.f90
irmsd/_fortran/fmods/strucrd.f90
irmsd/_fortran/fmods/rmsd_exposed.f90
irmsd/_fortran/crest_mods/hungarian.f90
irmsd/_fortran/crest_mods/CMakeLists.txt
irmsd/_fortran/crest_mods/atmasses.f90
irmsd/_fortran/crest_mods/floydwarshall.f90
irmsd/_fortran/crest_mods/geo.f90
irmsd/_fortran/crest_mods/dijkstra.f90
irmsd/_fortran/crest_mods/cn.f90
irmsd/_fortran/crest_mods/README.md
irmsd/_fortran/crest_mods/axis_module.f90
irmsd/_fortran/crest_mods/crest_pars.f90
irmsd/_fortran/crest_mods/miscdata.f90
irmsd/_fortran/crest_mods/canonical.f90
irmsd/_fortran/crest_mods/irmsd_module.f90
irmsd/_fortran/crest_mods/adjacency.f90
irmsd/_fortran/crest_mods/ls_rmsd.f90
irmsd/utils/xyz.py
irmsd/utils/io.py
irmsd/utils/__init__.py
irmsd/utils/utils.py
irmsd/utils/printouts.py
irmsd/.dylibs/libgfortran.5.dylib
irmsd/.dylibs/libquadmath.0.dylib
irmsd/.dylibs/libgcc_s.1.1.dylib
irmsd/sorting/representatives.py
irmsd/sorting/sort_by_value.py
irmsd/sorting/group_by.py
irmsd/sorting/__init__.py
irmsd/api/canonical_exposed.py
irmsd/api/__init__.py
irmsd/api/irmsd_exposed.py
irmsd/api/sorter_exposed.py
irmsd/api/cn_exposed.py
irmsd/api/rmsd_exposed.py
irmsd/api/axis_exposed.py
irmsd/bindings/canonical_exposed.py
irmsd/bindings/__init__.py
irmsd/bindings/irmsd_exposed.py
irmsd/bindings/sorter_exposed.py
irmsd/bindings/cn_exposed.py
irmsd/bindings/rmsd_exposed.py
irmsd/bindings/axis_exposed.py
