Metadata-Version: 2.2
Name: irmsd
Version: 0.1.1
Summary: irmsd: A package for the calculation of the permutation-invariant root-mean-square-deviation (RMSD) of atomic positions.
Author: Philipp Pracht, Tobias Kaczun
License:                    GNU LESSER GENERAL PUBLIC LICENSE
Project-URL: Homepage, https://github.com/pprcht/irmsd
Project-URL: Issues, https://github.com/pprcht/irmsd/issues
Requires-Python: >=3.10
Requires-Dist: numpy>=2.0
Provides-Extra: ase
Requires-Dist: ase>=3.22.1; extra == "ase"
Provides-Extra: rdkit
Requires-Dist: rdkit>=2025.9.2; extra == "rdkit"
Provides-Extra: dev
Requires-Dist: pytest; extra == "dev"
Requires-Dist: pytest-cov; extra == "dev"
Provides-Extra: docs
Requires-Dist: sphinx>=8.2.3; extra == "docs"
Requires-Dist: shibuya; extra == "docs"
Requires-Dist: myst-parser; extra == "docs"
